allauth_tim/__init__.py
allauth_tim/provider.py
allauth_tim/urls.py
allauth_tim/views.py
allauth_tim-1.0.1.dist-info/LICENSE
allauth_tim-1.0.1.dist-info/METADATA
allauth_tim-1.0.1.dist-info/WHEEL
allauth_tim-1.0.1.dist-info/top_level.txt
allauth_tim-1.0.1.dist-info/RECORD
